MANIFEST.in
README.md
setup.py
premailer/__init__.py
premailer/gorun_settings.py
premailer/premailer.py
premailer/test_premailer.py
premailer_cspw.egg-info/PKG-INFO
premailer_cspw.egg-info/SOURCES.txt
premailer_cspw.egg-info/dependency_links.txt
premailer_cspw.egg-info/entry_points.txt
premailer_cspw.egg-info/requires.txt
premailer_cspw.egg-info/top_level.txt
premailer_cspw.egg-info/zip-safe