Metadata-Version: 1.1
Name: premailer-cspw
Version: 1.2.2
Summary: Turns CSS blocks into style attributes
Home-page: http://github.com/peterbe/premailer
Author: Peter Bengtsson
Author-email: mail@peterbe.com
License: Python
Download-URL: http://github.com/peterbe/premailer
Keywords: html lxml email mail style
Platform: UNKNOWN
Classifier: Development Status :: 5 - Production/Stable
Classifier: Environment :: Other Environment
Classifier: Environment :: Web Environment
Classifier: Intended Audience :: Developers
Classifier: License :: OSI Approved :: Python Software Foundation License
Classifier: Operating System :: OS Independent
Classifier: Programming Language :: Python
Classifier: Topic :: Communications
Classifier: Topic :: Internet :: WWW/HTTP
Classifier: Topic :: Other/Nonlisted Topic
Classifier: Topic :: Software Development :: Libraries :: Python Modules
